trezor_gpg
