Metadata-Version: 1.1
Name: trezor-gpg
Version: 0.0.6
Summary: Use Trezor for GPG passphrases
Home-page: https://github.com/rendaw/python-trezor-gpg
Author: rendaw
Author-email: spoo@zarbosoft.com
License: BSD
Download-URL: https://github.com/rendaw/python-trezor-gpg/tarball/v0.0.6
Platform: UNKNOWN
Classifier: License :: OSI Approved :: BSD License
